snappy/__init__.py
snappy/__main__.py
snappy/hadoop_snappy.py
snappy/snappy.py
snappy/snappy_formats.py
python_snappy-0.7.0.dist-info/AUTHORS
python_snappy-0.7.0.dist-info/LICENSE
python_snappy-0.7.0.dist-info/METADATA
python_snappy-0.7.0.dist-info/WHEEL
python_snappy-0.7.0.dist-info/top_level.txt
python_snappy-0.7.0.dist-info/RECORD
